faultguard.py
faultguard-1.1.1.dist-info/LICENSE
faultguard-1.1.1.dist-info/METADATA
faultguard-1.1.1.dist-info/WHEEL
faultguard-1.1.1.dist-info/top_level.txt
faultguard-1.1.1.dist-info/RECORD
