Metadata-Version: 2.1
Name: faultguard
Version: 1.1.1
Summary: Rescuing data from abrubt process termination in python.
Home-page: https://github.com/2xB/faultguard
Author: Benedikt Bieringer
Author-email: 2xB.coding@wwu.de
License: BSD 3-Clause License
Classifier: Programming Language :: Python :: 3
Classifier: License :: OSI Approved :: BSD License
Classifier: Operating System :: OS Independent
Classifier: Intended Audience :: Developers
License-File: LICENSE
